LICENSE
README.md
setup.cfg
setup.py
aiogtrans/__init__.py
aiogtrans/cache.py
aiogtrans/client.py
aiogtrans/constants.py
aiogtrans/models.py
aiogtrans/urls.py
aiogtrans.egg-info/PKG-INFO
aiogtrans.egg-info/SOURCES.txt
aiogtrans.egg-info/dependency_links.txt
aiogtrans.egg-info/requires.txt
aiogtrans.egg-info/top_level.txt