Metadata-Version: 2.1
Name: aiogtrans
Version: 1.1.6
Summary: An async and updated version of the googletrans package.
Home-page: https://github.com/Leg3ndary/aiogtrans
Author: Ben Z
Author-email: bleg3ndary@gmail.com
License: MIT
Keywords: google translate translator async
Classifier: Development Status :: 5 - Production/Stable
Classifier: Intended Audience :: Education
Classifier: Intended Audience :: End Users/Desktop
Classifier: License :: Freeware
Classifier: Operating System :: POSIX
Classifier: Operating System :: Microsoft :: Windows
Classifier: Operating System :: MacOS :: MacOS X
Classifier: Topic :: Education
Classifier: Programming Language :: Python
Classifier: Programming Language :: Python :: 3.9
Requires-Python: >=3.9
License-File: LICENSE
Requires-Dist: httpx<=0.23.0
Requires-Dist: setuptools==58.1.0
